sips/__init__.py
sips-0.14.2.dist-info/LICENSE
sips-0.14.2.dist-info/METADATA
sips-0.14.2.dist-info/WHEEL
sips-0.14.2.dist-info/top_level.txt
sips-0.14.2.dist-info/RECORD
