Metadata-Version: 2.1
Name: sips
Version: 0.14.2
Summary: tools for quantitative sports analysis
Home-page: https://github.com/anandijain/sips
Author: Anand Jain
Author-email: anandj@uchicago.edu
License: UNKNOWN
Platform: UNKNOWN
Requires-Python: >=3.6
Requires-Dist: pandas
Requires-Dist: requests
Requires-Dist: beautifulsoup4
Requires-Dist: numpy
Requires-Dist: scikit-learn
Requires-Dist: requests-futures
Requires-Dist: google-cloud-profiler
Requires-Dist: lxml
Requires-Dist: flask
